pySATSI/__init__.py
pySATSI/pySATSI.py
pySATSI/functions/__init__.py
pySATSI/functions/bootmech.py
pySATSI/functions/checkerboard.py
pySATSI/functions/default_params.py
pySATSI/functions/file_io.py
pySATSI/functions/fun.py
pySATSI/functions/gridding.py
pySATSI/functions/knee.py
pySATSI/functions/mech.py
pySATSI/functions/plotting.py
pySATSI/functions/stress.py
pySATSI/functions/colormaps/colorwheel.txt
pySATSI/functions/colormaps/rainbow.txt
pysatsi-0.2.1.dist-info/METADATA
pysatsi-0.2.1.dist-info/WHEEL
pysatsi-0.2.1.dist-info/entry_points.txt
pysatsi-0.2.1.dist-info/licenses/LICENSE.md
pysatsi-0.2.1.dist-info/RECORD
