Metadata-Version: 2.4
Name: pySATSI
Version: 0.2.1
Summary: Python package for focal mechanism stress inversions
Project-URL: Homepage, https://code.usgs.gov/esc/pySATSI
Project-URL: Issues, https://code.usgs.gov/esc/pySATSI/-/issues
Author-email: "Robert J. Skoumal" <rskoumal@usgs.gov>
License-Expression: CC0-1.0
License-File: LICENSE.md
Classifier: Operating System :: OS Independent
Classifier: Programming Language :: Python :: 3
Requires-Python: >=3.8
Requires-Dist: numpy<2.0
Requires-Dist: pandas
Requires-Dist: scikit-learn
Requires-Dist: scipy
Provides-Extra: plot
Requires-Dist: matplotlib; extra == 'plot'
